tristate20/__init__.py
tristate20/tristate20.py
tristate20-0.0.0a2.dist-info/LICENSE
tristate20-0.0.0a2.dist-info/METADATA
tristate20-0.0.0a2.dist-info/WHEEL
tristate20-0.0.0a2.dist-info/top_level.txt
tristate20-0.0.0a2.dist-info/RECORD
