Metadata-Version: 2.1
Name: tristate20
Version: 0.0.0a2
Summary: TRISTATE20 Dataset
Author: Jackson Burns
License: MIT
Project-URL: Homepage, https://github.com/QuantumPioneer/tristate20
Classifier: Programming Language :: Python :: 3
Requires-Python: >=3.8
License-File: LICENSE
Requires-Dist: dill
Requires-Dist: peewee
Provides-Extra: demos
Requires-Dist: jupyter ; extra == 'demos'
Provides-Extra: dev
Requires-Dist: black ; extra == 'dev'
Requires-Dist: isort ; extra == 'dev'
Requires-Dist: pytest ; extra == 'dev'
